boox/__init__.py
boox/client.py
boox/core.py
boox/api/__init__.py
boox/api/config_users.py
boox/api/core.py
boox/api/users.py
boox/models/__init__.py
boox/models/base.py
boox/models/config_users.py
boox/models/enums.py
boox/models/protocols.py
boox/models/users.py
pybooxdrop-0.6.1.dist-info/METADATA
pybooxdrop-0.6.1.dist-info/WHEEL
pybooxdrop-0.6.1.dist-info/licenses/LICENSE
pybooxdrop-0.6.1.dist-info/RECORD
