Metadata-Version: 2.4
Name: pybooxdrop
Version: 0.6.1
Summary: A friendly Python wrapper for the BOOXDrop API — unofficial, but built with care.
Project-URL: Source, https://github.com/filipgodlewski/pybooxdrop
Project-URL: Issues, https://github.com/filipgodlewski/pybooxdrop/issues
Author-email: Filip Godlewski <54432731+filipgodlewski@users.noreply.github.com>
License-Expression: MIT
License-File: LICENSE
Keywords: api-wrapper,boox,booxdrop,ebook-reader,file-transfer,onyx,python-wrapper
Classifier: Intended Audience :: Developers
Classifier: License :: OSI Approved :: MIT License
Classifier: Operating System :: OS Independent
Classifier: Programming Language :: Python :: 3.12
Classifier: Programming Language :: Python :: 3.13
Classifier: Topic :: Software Development :: Libraries
Classifier: Topic :: System :: Networking
Classifier: Topic :: Utilities
Requires-Python: >=3.12
Requires-Dist: pydantic[email]>=2.11.7
